LICENSE.md
mathhole/__init__.py
mathhole/_matrix.py
mathhole-0.0.2.dist-info/METADATA
mathhole-0.0.2.dist-info/WHEEL
mathhole-0.0.2.dist-info/LICENSE.md
mathhole-0.0.2.dist-info/RECORD
