Metadata-Version: 2.1
Name: mathhole
Version: 0.0.2
Summary: An extremely bad, unintelligent math library for a moron to learn. Please don't use and if you do, it is at your own risk.
Home-page: https://github.com/aaronclong/mathhole
License: DBAD
Author: Aaron Long
Author-email: aaron.long.c@gmail.com
Requires-Python: >=3.8,<4.0
Classifier: License :: Other/Proprietary License
Classifier: Programming Language :: Python :: 3
Classifier: Programming Language :: Python :: 3.8
Classifier: Programming Language :: Python :: 3.9
Classifier: Programming Language :: Python :: 3.10
Classifier: Programming Language :: Python :: 3.11
Project-URL: Repository, https://github.com/aaronclong/mathhole
